{
  "num_layers": 1,
  "model": "Attn",
  "dataset": "kidnap",
  "hidden_size": 50,
  "n_outputs": 10,
  "filter_sizes": [2, 3, 4],
  "num_filters": 10,
  "art_filter_sizes": [2, 3],
  "art_num_filters": 10,
  "pretrain": true,
  "attention_size": 100,
  "embedding_size": 300,
  "learning_rate": 0.00008,
  "keep_ratio": 0.75,
  "epochs": 30,
  "cell": "GRU",
  "task": "detect",
  "entity_keep_ratio": 0.75,
  "entity_learning_rate": 0.0001,
  "entity_num_filters": 3,
  "batch_size": 5,
  "sub_task": "train",
  "max_length": 500,
  "sentences": true
}
